aih/__init__.py
aih/aih.py
utils/face_utils.py
aih_dev-0.2.1.dist-info/METADATA
aih_dev-0.2.1.dist-info/WHEEL
aih_dev-0.2.1.dist-info/top_level.txt
aih_dev-0.2.1.dist-info/RECORD
