Metadata-Version: 2.1
Name: aih-dev
Version: 0.2.1
Summary: UNKNOWN
Home-page: UNKNOWN
Author: dien.duong
Author-email: duongngocdien@gmail.com
License: MIT
Platform: UNKNOWN
Requires-Dist: PyJWT
Requires-Dist: requests
